MANIFEST.in
README.md
VERSION
requirements.txt
setup.cfg
setup.py
rhasspy_asr_pocketsphinx_hermes.egg-info/PKG-INFO
rhasspy_asr_pocketsphinx_hermes.egg-info/SOURCES.txt
rhasspy_asr_pocketsphinx_hermes.egg-info/dependency_links.txt
rhasspy_asr_pocketsphinx_hermes.egg-info/entry_points.txt
rhasspy_asr_pocketsphinx_hermes.egg-info/requires.txt
rhasspy_asr_pocketsphinx_hermes.egg-info/top_level.txt
rhasspyasr_pocketsphinx_hermes/__init__.py
rhasspyasr_pocketsphinx_hermes/__main__.py
tests/__init__.py
tests/test_rhasspyasr_pocketsphinx_hermes.py