Metadata-Version: 2.1
Name: rhasspy-asr-pocketsphinx-hermes
Version: 0.1.4
Summary: UNKNOWN
Home-page: https://github.com/rhasspy/rhasspy-asr-pocketsphinx-hermes
Author: Michael Hansen
Author-email: hansen.mike@gmail.com
License: UNKNOWN
Platform: UNKNOWN
Classifier: Programming Language :: Python :: 3
Classifier: License :: OSI Approved :: MIT License
Requires-Python: >=3.7
